simple_gltf/__init__.py
simple_gltf-0.1.0.dist-info/LICENSE
simple_gltf-0.1.0.dist-info/METADATA
simple_gltf-0.1.0.dist-info/WHEEL
simple_gltf-0.1.0.dist-info/RECORD
