Metadata-Version: 2.1
Name: simple-gltf
Version: 0.1.0
Summary: A pythonic interface for parsing gltf/glb files based on pygltflib. 
Home-page: https://github.com/turtleizzy/simple_gltf
Author: TurtleIzzy
Author-email: agnimon@gmail.com
Requires-Python: >=3.9,<4.0
Classifier: License :: OSI Approved :: MIT License
Classifier: Operating System :: OS Independent
Classifier: Programming Language :: Python :: 3
Classifier: Programming Language :: Python :: 3.9
Classifier: Programming Language :: Python :: 3.10
Classifier: Programming Language :: Python :: 3.11
Classifier: Programming Language :: Python :: 3.12
Classifier: Programming Language :: Python :: 3.13
Requires-Dist: numpy
Requires-Dist: pygltflib
Project-URL: Repository, https://github.com/turtleizzy/simple_gltf
